robot_selfheal/SelfHealListener.py
robot_selfheal/__init__.py
robot_selfheal/candidate_algo.py
robot_selfheal/cli.py
robot_selfheal/config.json
robot_selfheal/self_healing_agent.py
robot_selfheal-2.1.0.dist-info/licenses/LICENSE
robot_selfheal-2.1.0.dist-info/METADATA
robot_selfheal-2.1.0.dist-info/WHEEL
robot_selfheal-2.1.0.dist-info/entry_points.txt
robot_selfheal-2.1.0.dist-info/top_level.txt
robot_selfheal-2.1.0.dist-info/RECORD
