Metadata-Version: 2.4
Name: robot-selfheal
Version: 2.1.0
Summary: Robot Framework Self-Healing Library for automated test maintenance
Home-page: https://github.com/samarthindex9/selfhealing_library/tree/pypi-packaging
Author: Samarth Math, Vikas Gupta, Onkar Pawar
Author-email: Samarth Math <samarth.math@indexnine.com>, Vikas Gupta <vikas.gupta@indexnine.com>, Onkar Pawar <onkar.pawar@indexnine.com>
Maintainer-email: Samarth Math <samarth.math@indexnine.com>, Vikas Gupta <vikas.gupta@indexnine.com>, Onkar Pawar <onkar.pawar@indexnine.com>
License-Expression: MIT
Project-URL: Homepage, https://github.com/samarthindex9/selfhealing_library
Project-URL: Documentation, https://github.com/samarthindex9/selfhealing_library/blob/pypi-packaging/README.md
Project-URL: Repository, https://github.com/samarthindex9/selfhealing_library
Project-URL: Bug Tracker, https://github.com/samarthindex9/selfhealing_library/issues
Keywords: robotframework,selenium,testing,automation,self-healing,locator,web-testing,ai,machine-learning,test-automation,quality-assurance,xpath,ui-testing
Classifier: Development Status :: 4 - Beta
Classifier: Intended Audience :: Developers
Classifier: Intended Audience :: Information Technology
Classifier: Operating System :: OS Independent
Classifier: Operating System :: Microsoft :: Windows
Classifier: Operating System :: POSIX :: Linux
Classifier: Operating System :: MacOS
Classifier: Programming Language :: Python :: 3
Classifier: Programming Language :: Python :: 3.8
Classifier: Programming Language :: Python :: 3.9
Classifier: Programming Language :: Python :: 3.10
Classifier: Programming Language :: Python :: 3.11
Classifier: Programming Language :: Python :: 3.12
Classifier: Programming Language :: Python :: 3 :: Only
Classifier: Topic :: Software Development :: Testing
Classifier: Topic :: Software Development :: Testing :: Acceptance
Classifier: Topic :: Software Development :: Testing :: Unit
Classifier: Topic :: Software Development :: Quality Assurance
Classifier: Topic :: Internet :: WWW/HTTP :: Browsers
Classifier: Topic :: Scientific/Engineering :: Artificial Intelligence
Classifier: Framework :: Robot Framework
Classifier: Framework :: Robot Framework :: Library
Classifier: Framework :: Robot Framework :: Tool
Classifier: Environment :: Console
Classifier: Natural Language :: English
Classifier: Typing :: Typed
Requires-Python: >=3.8
License-File: LICENSE
Requires-Dist: robotframework>=6.1.1
Requires-Dist: robotframework-seleniumlibrary>=6.1.0
Requires-Dist: beautifulsoup4>=4.12.2
Requires-Dist: rapidfuzz>=3.3.1
Requires-Dist: python-dotenv>=1.0.0
Requires-Dist: openai>=1.3.5
Requires-Dist: requests>=2.31.0
Requires-Dist: lxml>=4.9.3
Provides-Extra: dev
Requires-Dist: black>=23.11.0; extra == "dev"
Requires-Dist: pylint>=3.0.2; extra == "dev"
Requires-Dist: pytest>=7.4.3; extra == "dev"
Requires-Dist: twine>=4.0.0; extra == "dev"
Requires-Dist: build>=0.10.0; extra == "dev"
Dynamic: author
Dynamic: home-page
Dynamic: license-file
Dynamic: requires-python
